{
  "generated_at": "2026-04-17T20:01:40.769Z",
  "artifact_version": "v1",
  "engine": {
    "engine_family": "mlb_ai_ranker",
    "engine_version": "v1",
    "active_policy": "edge_gte_0_04_no_cap_challenger",
    "engine_state": "shadow_challenger",
    "model_lock_status": "ranker_quality_filtered_challenger",
    "trusted_for_live_betting": false
  },
  "selection_contract": "edge_gte_0_04_no_cap_challenger",
  "season": 2026,
  "results_through": "2026-04-16",
  "rows": [
    {
      "board_date": "2026-03-20",
      "bets": 1,
      "selected_bets": 1,
      "settled_bets": 1,
      "pending_bets": 0,
      "wins": 0,
      "losses": 1,
      "pushes": 0,
      "win_rate": 0,
      "avg_price": -148,
      "avg_win_price": null,
      "units": -1,
      "roi": -1,
      "cumulative_units": -1,
      "drawdown_to_date": -1,
      "selection_pct": 0.018519
    },
    {
      "board_date": "2026-03-21",
      "bets": 5,
      "selected_bets": 5,
      "settled_bets": 5,
      "pending_bets": 0,
      "wins": 2,
      "losses": 3,
      "pushes": 0,
      "win_rate": 0.4,
      "avg_price": -139,
      "avg_win_price": -138.5,
      "units": -1.555034,
      "roi": -0.311007,
      "cumulative_units": -2.555034,
      "drawdown_to_date": -2.555034,
      "selection_pct": 0.064103
    },
    {
      "board_date": "2026-03-22",
      "bets": 5,
      "selected_bets": 5,
      "settled_bets": 5,
      "pending_bets": 0,
      "wins": 3,
      "losses": 2,
      "pushes": 0,
      "win_rate": 0.6,
      "avg_price": -134.6,
      "avg_win_price": -132.67,
      "units": 0.263099,
      "roi": 0.05262,
      "cumulative_units": -2.291935,
      "drawdown_to_date": -2.291935,
      "selection_pct": 0.064103
    },
    {
      "board_date": "2026-03-23",
      "bets": 7,
      "selected_bets": 7,
      "settled_bets": 7,
      "pending_bets": 0,
      "wins": 5,
      "losses": 2,
      "pushes": 0,
      "win_rate": 0.714286,
      "avg_price": -139.57,
      "avg_win_price": -140.6,
      "units": 1.564958,
      "roi": 0.223565,
      "cumulative_units": -0.726977,
      "drawdown_to_date": -0.726977,
      "selection_pct": 0.097222
    },
    {
      "board_date": "2026-03-24",
      "bets": 2,
      "selected_bets": 2,
      "settled_bets": 2,
      "pending_bets": 0,
      "wins": 1,
      "losses": 1,
      "pushes": 0,
      "win_rate": 0.5,
      "avg_price": -213.5,
      "avg_win_price": -135,
      "units": -0.259259,
      "roi": -0.12963,
      "cumulative_units": -0.986236,
      "drawdown_to_date": -0.986236,
      "selection_pct": 0.041667
    },
    {
      "board_date": "2026-03-25",
      "bets": 0,
      "selected_bets": 0,
      "settled_bets": 0,
      "pending_bets": 0,
      "wins": 0,
      "losses": 0,
      "pushes": 0,
      "win_rate": null,
      "avg_price": null,
      "avg_win_price": null,
      "units": 0,
      "roi": null,
      "cumulative_units": -0.986236,
      "drawdown_to_date": -0.986236,
      "selection_pct": 0
    },
    {
      "board_date": "2026-03-26",
      "bets": 6,
      "selected_bets": 6,
      "settled_bets": 6,
      "pending_bets": 0,
      "wins": 4,
      "losses": 2,
      "pushes": 0,
      "win_rate": 0.666667,
      "avg_price": -96.67,
      "avg_win_price": -77.5,
      "units": 1.246031,
      "roi": 0.207672,
      "cumulative_units": 0.259795,
      "drawdown_to_date": 0,
      "selection_pct": 0.090909
    },
    {
      "board_date": "2026-03-27",
      "bets": 3,
      "selected_bets": 3,
      "settled_bets": 3,
      "pending_bets": 0,
      "wins": 3,
      "losses": 0,
      "pushes": 0,
      "win_rate": 1,
      "avg_price": -138.67,
      "avg_win_price": -138.67,
      "units": 2.165851,
      "roi": 0.72195,
      "cumulative_units": 2.425646,
      "drawdown_to_date": 0,
      "selection_pct": 0.0625
    },
    {
      "board_date": "2026-03-28",
      "bets": 6,
      "selected_bets": 6,
      "settled_bets": 6,
      "pending_bets": 0,
      "wins": 4,
      "losses": 2,
      "pushes": 0,
      "win_rate": 0.666667,
      "avg_price": -91.17,
      "avg_win_price": -140.25,
      "units": 0.860847,
      "roi": 0.143474,
      "cumulative_units": 3.286493,
      "drawdown_to_date": 0,
      "selection_pct": 0.066667
    },
    {
      "board_date": "2026-03-29",
      "bets": 3,
      "selected_bets": 3,
      "settled_bets": 3,
      "pending_bets": 0,
      "wins": 1,
      "losses": 2,
      "pushes": 0,
      "win_rate": 0.333333,
      "avg_price": -44,
      "avg_win_price": -136,
      "units": -1.264706,
      "roi": -0.421569,
      "cumulative_units": 2.021787,
      "drawdown_to_date": -1.264706,
      "selection_pct": 0.041667
    },
    {
      "board_date": "2026-03-30",
      "bets": 5,
      "selected_bets": 5,
      "settled_bets": 5,
      "pending_bets": 0,
      "wins": 2,
      "losses": 3,
      "pushes": 0,
      "win_rate": 0.4,
      "avg_price": -161.8,
      "avg_win_price": -131.5,
      "units": -1.478009,
      "roi": -0.295602,
      "cumulative_units": 0.543778,
      "drawdown_to_date": -2.742715,
      "selection_pct": 0.059524
    },
    {
      "board_date": "2026-03-31",
      "bets": 3,
      "selected_bets": 3,
      "settled_bets": 3,
      "pending_bets": 0,
      "wins": 3,
      "losses": 0,
      "pushes": 0,
      "win_rate": 1,
      "avg_price": -222.33,
      "avg_win_price": -222.33,
      "units": 1.528396,
      "roi": 0.509465,
      "cumulative_units": 2.072174,
      "drawdown_to_date": -1.214319,
      "selection_pct": 0.035714
    },
    {
      "board_date": "2026-04-01",
      "bets": 7,
      "selected_bets": 7,
      "settled_bets": 7,
      "pending_bets": 0,
      "wins": 3,
      "losses": 4,
      "pushes": 0,
      "win_rate": 0.428571,
      "avg_price": -166,
      "avg_win_price": -188.33,
      "units": -2.237254,
      "roi": -0.319608,
      "cumulative_units": -0.16508,
      "drawdown_to_date": -3.451573,
      "selection_pct": 0.077778
    },
    {
      "board_date": "2026-04-02",
      "bets": 0,
      "selected_bets": 0,
      "settled_bets": 0,
      "pending_bets": 0,
      "wins": 0,
      "losses": 0,
      "pushes": 0,
      "win_rate": null,
      "avg_price": null,
      "avg_win_price": null,
      "units": 0,
      "roi": null,
      "cumulative_units": -0.16508,
      "drawdown_to_date": -3.451573,
      "selection_pct": 0
    },
    {
      "board_date": "2026-04-03",
      "bets": 1,
      "selected_bets": 1,
      "settled_bets": 1,
      "pending_bets": 0,
      "wins": 1,
      "losses": 0,
      "pushes": 0,
      "win_rate": 1,
      "avg_price": -285,
      "avg_win_price": -285,
      "units": 0.350877,
      "roi": 0.350877,
      "cumulative_units": 0.185797,
      "drawdown_to_date": -3.100696,
      "selection_pct": 0.011905
    },
    {
      "board_date": "2026-04-04",
      "bets": 4,
      "selected_bets": 4,
      "settled_bets": 4,
      "pending_bets": 0,
      "wins": 4,
      "losses": 0,
      "pushes": 0,
      "win_rate": 1,
      "avg_price": -61.75,
      "avg_win_price": -61.75,
      "units": 3.291941,
      "roi": 0.822985,
      "cumulative_units": 3.477738,
      "drawdown_to_date": 0,
      "selection_pct": 0.041667
    },
    {
      "board_date": "2026-04-05",
      "bets": 10,
      "selected_bets": 10,
      "settled_bets": 10,
      "pending_bets": 0,
      "wins": 6,
      "losses": 4,
      "pushes": 0,
      "win_rate": 0.6,
      "avg_price": -71.1,
      "avg_win_price": -1.67,
      "units": 2.429295,
      "roi": 0.242929,
      "cumulative_units": 5.907033,
      "drawdown_to_date": 0,
      "selection_pct": 0.104167
    },
    {
      "board_date": "2026-04-06",
      "bets": 4,
      "selected_bets": 4,
      "settled_bets": 4,
      "pending_bets": 0,
      "wins": 3,
      "losses": 1,
      "pushes": 0,
      "win_rate": 0.75,
      "avg_price": -27.5,
      "avg_win_price": 30,
      "units": 2.050272,
      "roi": 0.512568,
      "cumulative_units": 7.957305,
      "drawdown_to_date": 0,
      "selection_pct": 0.051282
    },
    {
      "board_date": "2026-04-07",
      "bets": 4,
      "selected_bets": 4,
      "settled_bets": 4,
      "pending_bets": 0,
      "wins": 1,
      "losses": 3,
      "pushes": 0,
      "win_rate": 0.25,
      "avg_price": -75.75,
      "avg_win_price": -138,
      "units": -2.275362,
      "roi": -0.568841,
      "cumulative_units": 5.681943,
      "drawdown_to_date": -2.275362,
      "selection_pct": 0.044444
    },
    {
      "board_date": "2026-04-08",
      "bets": 6,
      "selected_bets": 6,
      "settled_bets": 6,
      "pending_bets": 0,
      "wins": 6,
      "losses": 0,
      "pushes": 0,
      "win_rate": 1,
      "avg_price": -50.17,
      "avg_win_price": -50.17,
      "units": 5.361804,
      "roi": 0.893634,
      "cumulative_units": 11.043747,
      "drawdown_to_date": 0,
      "selection_pct": 0.066667
    },
    {
      "board_date": "2026-04-09",
      "bets": 2,
      "selected_bets": 2,
      "settled_bets": 2,
      "pending_bets": 0,
      "wins": 2,
      "losses": 0,
      "pushes": 0,
      "win_rate": 1,
      "avg_price": -126,
      "avg_win_price": -126,
      "units": 1.587302,
      "roi": 0.793651,
      "cumulative_units": 12.631049,
      "drawdown_to_date": 0,
      "selection_pct": 0.055556
    },
    {
      "board_date": "2026-04-10",
      "bets": 7,
      "selected_bets": 7,
      "settled_bets": 7,
      "pending_bets": 0,
      "wins": 4,
      "losses": 3,
      "pushes": 0,
      "win_rate": 0.571429,
      "avg_price": -56.43,
      "avg_win_price": -56.75,
      "units": 0.971588,
      "roi": 0.138798,
      "cumulative_units": 13.602637,
      "drawdown_to_date": 0,
      "selection_pct": 0.079545
    },
    {
      "board_date": "2026-04-11",
      "bets": 4,
      "selected_bets": 4,
      "settled_bets": 4,
      "pending_bets": 0,
      "wins": 2,
      "losses": 2,
      "pushes": 0,
      "win_rate": 0.5,
      "avg_price": -79.5,
      "avg_win_price": -11,
      "units": -0.095775,
      "roi": -0.023944,
      "cumulative_units": 13.506862,
      "drawdown_to_date": -0.095775,
      "selection_pct": 0.044444
    },
    {
      "board_date": "2026-04-12",
      "bets": 6,
      "selected_bets": 6,
      "settled_bets": 6,
      "pending_bets": 0,
      "wins": 3,
      "losses": 3,
      "pushes": 0,
      "win_rate": 0.5,
      "avg_price": -118.5,
      "avg_win_price": -77.67,
      "units": -0.565821,
      "roi": -0.094303,
      "cumulative_units": 12.941041,
      "drawdown_to_date": -0.661596,
      "selection_pct": 0.066667
    },
    {
      "board_date": "2026-04-13",
      "bets": 4,
      "selected_bets": 4,
      "settled_bets": 4,
      "pending_bets": 0,
      "wins": 2,
      "losses": 2,
      "pushes": 0,
      "win_rate": 0.5,
      "avg_price": -75.5,
      "avg_win_price": -3.5,
      "units": -0.02,
      "roi": -0.005,
      "cumulative_units": 12.921041,
      "drawdown_to_date": -0.681596,
      "selection_pct": 0.066667
    },
    {
      "board_date": "2026-04-14",
      "bets": 7,
      "selected_bets": 7,
      "settled_bets": 7,
      "pending_bets": 0,
      "wins": 3,
      "losses": 4,
      "pushes": 0,
      "win_rate": 0.428571,
      "avg_price": -55,
      "avg_win_price": -134.33,
      "units": -1.766558,
      "roi": -0.252365,
      "cumulative_units": 11.154483,
      "drawdown_to_date": -2.448154,
      "selection_pct": 0.077778
    },
    {
      "board_date": "2026-04-15",
      "bets": 5,
      "selected_bets": 5,
      "settled_bets": 5,
      "pending_bets": 0,
      "wins": 1,
      "losses": 4,
      "pushes": 0,
      "win_rate": 0.2,
      "avg_price": -176.2,
      "avg_win_price": -121,
      "units": -3.173554,
      "roi": -0.634711,
      "cumulative_units": 7.980929,
      "drawdown_to_date": -5.621708,
      "selection_pct": 0.05814
    },
    {
      "board_date": "2026-04-16",
      "bets": 4,
      "selected_bets": 4,
      "settled_bets": 4,
      "pending_bets": 0,
      "wins": 4,
      "losses": 0,
      "pushes": 0,
      "win_rate": 1,
      "avg_price": 1.25,
      "avg_win_price": 1.25,
      "units": 5.482282,
      "roi": 1.370571,
      "cumulative_units": 13.463211,
      "drawdown_to_date": -0.139426,
      "selection_pct": 0.071429
    },
    {
      "board_date": "2026-04-17",
      "bets": 0,
      "selected_bets": 11,
      "settled_bets": 0,
      "pending_bets": 11,
      "wins": 0,
      "losses": 0,
      "pushes": 0,
      "win_rate": null,
      "avg_price": null,
      "avg_win_price": null,
      "units": 0,
      "roi": null,
      "cumulative_units": 13.463211,
      "drawdown_to_date": -0.139426,
      "selection_pct": 0.123596
    }
  ],
  "summary": {
    "bets": 121,
    "selected_bets": 132,
    "settled_bets": 121,
    "pending_bets": 11,
    "wins": 73,
    "losses": 48,
    "pushes": 0,
    "units": 13.463212,
    "roi": 0.111266
  }
}
